Workbook

Sheet Resumen
A1: SALUD DE INVENTARIO — VICTOR
A2: Snapshot al 26-05-2026 · Fuente: Informe ERP · 151 SKUs
A4: MÉTRICA | B4: VALOR
A5: Total SKUs | B5: =COUNTA(Detalle!A2:A1000) -> 151
A6: Valor total inmovilizado (al costo, CLP) | B6: =SUMPRODUCT(Detalle!D2:D200,Detalle!E2:E200) -> 9829500
A7: Costo unitario promedio (CLP) | B7: =AVERAGE(Detalle!E2:E200) -> 10239.808
A8: Costo unitario máximo (CLP) | B8: =MAX(Detalle!E2:E200) -> 93036
A9: Stock total (unidades) | B9: =SUM(Detalle!D2:D200) -> 1910
A10: SKUs en stock crítico (1-3 u) | B10: =COUNTIFS(Detalle!D2:D200,">=1",Detalle!D2:D200,"<=3") -> 77
A11: SKUs en stock medio (4-10 u) | B11: =COUNTIFS(Detalle!D2:D200,">=4",Detalle!D2:D200,"<=10") -> 53
A12: SKUs en stock sano (>10 u) | B12: =COUNTIF(Detalle!D2:D200,">10") -> 21
A13: SKUs agotados (stock = 0) | B13: =COUNTIF(Detalle!D2:D200,0) -> 0
A14: SKUs con reposición pendiente | B14: =COUNTIF(Detalle!F2:F200,">0") -> 12
A17: CÓMO LEER ESTE ARCHIVO
A18: • Hoja 'Detalle': 151 SKUs con código, descripción, familia, stock, costo unitario y valor inmovilizado.
A19: • Hoja 'Por Familia': agrupación por familia de producto con totales.
A20: • Hoja 'Top Inmovilizado': los 20 SKUs con mayor capital dormido — prioridad para entender rotación.
A21: • Clasificación de riesgo: CRÍTICO (1-3 u) · MEDIO (4-10 u) · SANO (>10 u) · AGOTADO (0 u).
A22: • Falta: precio de venta por marketplace + comisiones + costo logístico para calcular margen neto.

Sheet Detalle
A1: Código | B1: Descripción | C1: Familia | D1: Stock | E1: Costo unit (CLP) | F1: Pend. recepción | G1: Fecha recepción | H1: Pend. entrega | I1: Stock futuro | J1: Valor inmovilizado (CLP) | K1: Riesgo stock
A2: 040201005 | B2: T-LLAVE MONOMANDO LAVAPLATOS VERTICAL PROFESIONAL | C2: 04 - Válvulas y llaves | D2: 1 | E2: 35656 | F2: 0 | G2: 0 | H2: 0 | I2: 0 | J2: =D2*E2 -> 35656 | K2: =IF(D2=0,"AGOTADO",IF(D2<=3,"CRÍTICO",IF(D2<=10,"MEDIO","SANO"))) -> CRÍTICO
A3: 020102008 | B3: W-WC | C3: 02 - Lavaplatos | D3: 1 | E3: 30000 | F3: 0 | G3: 0 | H3: 0 | I3: 0 | J3: =D3*E3 -> 30000 | K3: =IF(D3=0,"AGOTADO",IF(D3<=3,"CRÍTICO",IF(D3<=10,"MEDIO","SANO"))) -> CRÍTICO
A4: 915100122 | B4: Pack Lavaplatos 80x44 Secador Izquierdo + Rejilla Agustina + Llave Vertical Inox | C4: 91 - Rejillas y misc | D4: 1 | E4: 24060 | F4: 24060 | G4: 0 | H4: 0 | I4: 0 | J4: =D4*E4 -> 24060 | K4: =IF(D4=0,"AGOTADO",IF(D4<=3,"CRÍTICO",IF(D4<=10,"MEDIO","SANO"))) -> CRÍTICO
A5: 010703007 | B5: T-ESPEJO 60X90 RECTANGULAR BORDE AZUL | C5: 01 - Accesorios baño/ducha | D5: 1 | E5: 18671 | F5: 0 | G5: 0 | H5: 0 | I5: 0 | J5: =D5*E5 -> 18671 | K5: =IF(D5=0,"AGOTADO",IF(D5<=3,"CRÍTICO",IF(D5<=10,"MEDIO","SANO"))) -> CRÍTICO
A6: 010102008 | B6: T-BARRA 3 APOYOS 90 MURO | C6: 01 - Accesorios baño/ducha | D6: 1 | E6: 15712 | F6: 0 | G6: 0 | H6: 0 | I6: 0 | J6: =D6*E6 -> 15712 | K6: =IF(D6=0,"AGOTADO",IF(D6<=3,"CRÍTICO",IF(D6<=10,"MEDIO","SANO"))) -> CRÍTICO
A7: 040202002 | B7: T-LLAVE MONOMANDO LAVATORIO ALTO NOTTE NEGRO | C7: 04 - Válvulas y llaves | D7: 1 | E7: 14015 | F7: 0 | G7: 0 | H7: 0 | I7: 0 | J7: =D7*E7 -> 14015 | K7: =IF(D7=0,"AGOTADO",IF(D7<=3,"CRÍTICO",IF(D7<=10,"MEDIO","SANO"))) -> CRÍTICO
A8: 010704017 | B8: T-MONOMANDO DUCHA NOTTE | C8: 01 - Accesorios baño/ducha | D8: 1 | E8: 12335 | F8: 0 | G8: 0 | H8: 0 | I8: 0 | J8: =D8*E8 -> 12335 | K8: =IF(D8=0,"AGOTADO",IF(D8<=3,"CRÍTICO",IF(D8<=10,"MEDIO","SANO"))) -> CRÍTICO
A9: 040203001 | B9: T-LLAVE MONOMANDO DUCHA AL MURO NOTTE NEGRO | C9: 04 - Válvulas y llaves | D9: 1 | E9: 10633 | F9: 0 | G9: 0 | H9: 0 | I9: 0 | J9: =D9*E9 -> 10633 | K9: =IF(D9=0,"AGOTADO",IF(D9<=3,"CRÍTICO",IF(D9<=10,"MEDIO","SANO"))) -> CRÍTICO
A10: 010702003 | B10: T-PAPELERO PEDAL 12 L | C10: 01 - Accesorios baño/ducha | D10: 1 | E10: 7123 | F10: 0 | G10: 0 | H10: 0 | I10: 0 | J10: =D10*E10 -> 7123 | K10: =IF(D10=0,"AGOTADO",IF(D10<=3,"CRÍTICO",IF(D10<=10,"MEDIO","SANO"))) -> CRÍTICO
A11: 010102003 | B11: T-BARRA DUCHA DESLIZABLE 65 CM | C11: 01 - Accesorios baño/ducha | D11: 1 | E11: 6060 | F11: 0 | G11: 0 | H11: 0 | I11: 0 | J11: =D11*E11 -> 6060 | K11: =IF(D11=0,"AGOTADO",IF(D11<=3,"CRÍTICO",IF(D11<=10,"MEDIO","SANO"))) -> CRÍTICO
A12: 010701013 | B12: T-PORTAPAPEL HIGIENICO INDUSTRIAL PLASTICO | C12: 01 - Accesorios baño/ducha | D12: 1 | E12: 5829 | F12: 0 | G12: 0 | H12: 0 | I12: 0 | J12: =D12*E12 -> 5829 | K12: =IF(D12=0,"AGOTADO",IF(D12<=3,"CRÍTICO",IF(D12<=10,"MEDIO","SANO"))) -> CRÍTICO
A13: 010302009 | B13: T-Asiento Tapa WC Modern | C13: 01 - Accesorios baño/ducha | D13: 1 | E13: 5666 | F13: 0 | G13: 0 | H13: 0 | I13: 0 | J13: =D13*E13 -> 5666 | K13: =IF(D13=0,"AGOTADO",IF(D13<=3,"CRÍTICO",IF(D13<=10,"MEDIO","SANO"))) -> CRÍTICO
... A152: 915100109 | B152: Rejilla Michele | C152: 91 - Rejillas y misc | D152: 315 | E152: 2000 | F152: 0 | G152: 0 | H152: 0 | I152: 0 | J152: =D152*E152 -> 630000 | K152: =IF(D152=0,"AGOTADO",IF(D152<=3,"CRÍTICO",IF(D152<=10,"MEDIO","SANO"))) -> SANO

Sheet Por Familia
A1: ANÁLISIS POR FAMILIA DE PRODUCTO
A3: Familia | B3: SKUs | C3: Stock total | D3: Valor inmovilizado (CLP) | E3: Costo unit promedio | F3: % del valor
A4: 04 - Válvulas y llaves | B4: 29 | C4: 421 | D4: 3725277 | E4: =IF(C4=0,0,D4/C4) -> 8848.639 | F4: =D4/SUM(D$4:D$11) -> 0.37898947
A5: 01 - Accesorios baño/ducha | B5: 65 | C5: 244 | D5: 2088416 | E5: =IF(C5=0,0,D5/C5) -> 8559.082 | F5: =D5/SUM(D$4:D$11) -> 0.21246411
A6: 91 - Rejillas y misc | B6: 16 | C6: 638 | D6: 1884992 | E6: =IF(C6=0,0,D6/C6) -> 2954.5329 | F6: =D6/SUM(D$4:D$11) -> 0.19176886
A7: 02 - Lavaplatos | B7: 20 | C7: 182 | D7: 1204618 | E7: =IF(C7=0,0,D7/C7) -> 6618.7802 | F7: =D7/SUM(D$4:D$11) -> 0.1225513
A8: 10 - Mamparas/duchas premium | B8: 4 | C8: 17 | D8: 485000 | E8: =IF(C8=0,0,D8/C8) -> 28529.412 | F8: =D8/SUM(D$4:D$11) -> 0.049341269
A9: 03 - WC y accesorios | B9: 15 | C9: 364 | D9: 433073 | E9: =IF(C9=0,0,D9/C9) -> 1189.761 | F9: =D9/SUM(D$4:D$11) -> 0.044058497
A10: 21 - Otros | B10: 1 | C10: 4 | D10: 8084 | E10: =IF(C10=0,0,D10/C10) -> 2021 | F10: =D10/SUM(D$4:D$11) -> 0.0008224223
A11: 1 - Sin clasificar | B11: 1 | C11: 40 | D11: 40 | E11: =IF(C11=0,0,D11/C11) -> 1 | F11: =D11/SUM(D$4:D$11) -> 4.069383e-06
A12: TOTAL | B12: =SUM(B4:B11) -> 151 | C12: =SUM(C4:C11) -> 1910 | D12: =SUM(D4:D11) -> 9829500 | F12: =SUM(F4:F11) -> 1

Sheet Top Inmovilizado
A1: TOP 20 SKUs POR VALOR INMOVILIZADO
A2: Estos son los SKUs donde tienes más capital dormido. Prioridad para verificar rotación real.
A4: # | B4: Código | C4: Descripción | D4: Stock | E4: Costo unit | F4: Valor inmov.
A5: 1 | B5: 040101001 | C5: C-VALVULA DESVIO DIVERTER 3 VIAS 1/2 3/8 | D5: 270 | E5: 7767 | F5: =D5*E5 -> 2097090
A6: 2 | B6: 915100109 | C6: Rejilla Michele | D6: 315 | E6: 2000 | F6: =D6*E6 -> 630000
A7: 3 | B7: 915100110 | C7: Canastillo Pascal | D7: 76 | E7: 4000 | F7: =D7*E7 -> 304000
A8: 4 | B8: 030102003 | C8: K-TOALLA INTERFOLEADA 200 UND POR PAQUETE | D8: 261 | E8: 1160 | F8: =D8*E8 -> 302760
A9: 5 | B9: 915100111 | C9: Rejilla Lavaplatos Fabricio | D9: 86 | E9: 3490 | F9: =D9*E9 -> 300140
A10: 6 | B10: 010703013 | C10: T-ESPEJO 70X100 CM, 3 LUCES LED DISTINTAS | D10: 4 | E10: 69990 | F10: =D10*E10 -> 279960
A11: 7 | B11: 020101002 | C11: C-Lavaplatos empotrado 37x32 Chocolate | D11: 49 | E11: 5000 | F11: =D11*E11 -> 245000
A12: 8 | B12: 100501027 | C12: T-Base curva 80x120 Der. | D12: 7 | E12: 35000 | F12: =D12*E12 -> 245000
A13: 9 | B13: 010501022 | C13: T-SHOWER DOOR 80X80X195 CUADRADO TRANSPARENTE | D13: 3 | E13: 80000 | F13: =D13*E13 -> 240000
A14: 10 | B14: 020101001 | C14: T-LAVAPLATOS SIMPLE EMPOTRADO 100X44 CM SECADOR DERECHO | D14: 17 | E14: 13427 | F14: =D14*E14 -> 228259
A15: 11 | B15: 020101002 | C15: T-LAVAPLATOS SIMPLE EMPOTRADO 100X44 CM SECADOR IZQUIERDO | D15: 17 | E15: 13219 | F15: =D15*E15 -> 224723
A16: 12 | B16: 010502005 | C16: T-MAMPARA DUCHA 120-140X190 CM | D16: 2 | E16: 93036 | F16: =D16*E16 -> 186072
... A24: 20 | B24: 010603004 | C24: T-RECEPTACULO DUCHA 80X80 CM | D24: 5 | E24: 23601 | F24: =D24*E24 -> 118005
